adam_authsession/__init__.py
adam_authsession/adam_authsession.py
adam_authsession-0.1.2.dist-info/METADATA
adam_authsession-0.1.2.dist-info/WHEEL
adam_authsession-0.1.2.dist-info/RECORD
